nat/meta/pypi.md
nat/plugins/strands/__init__.py
nat/plugins/strands/llm.py
nat/plugins/strands/register.py
nat/plugins/strands/strands_callback_handler.py
nat/plugins/strands/tool_wrapper.py
nvidia_nat_strands-1.5.0a20260130.dist-info/METADATA
nvidia_nat_strands-1.5.0a20260130.dist-info/WHEEL
nvidia_nat_strands-1.5.0a20260130.dist-info/entry_points.txt
nvidia_nat_strands-1.5.0a20260130.dist-info/top_level.txt
nvidia_nat_strands-1.5.0a20260130.dist-info/RECORD
