Metadata-Version: 2.4
Name: nvidia-nat-strands
Version: 1.5.0a20260130
Summary: Subpackage for AWS Strands integration in NeMo Agent toolkit
Author: NVIDIA Corporation
Maintainer: NVIDIA Corporation
License: Apache-2.0
Project-URL: documentation, https://docs.nvidia.com/nemo/agent-toolkit/latest/
Project-URL: source, https://github.com/NVIDIA/NeMo-Agent-Toolkit
Keywords: ai,rag,agents
Classifier: Programming Language :: Python
Classifier: Programming Language :: Python :: 3.11
Classifier: Programming Language :: Python :: 3.12
Classifier: Programming Language :: Python :: 3.13
Requires-Python: <3.14,>=3.11
Requires-Dist: nvidia-nat==v1.5.0a20260130
Requires-Dist: strands-agents~=1.17
Requires-Dist: strands-agents-tools~=0.2
